neuroglancer-2.41.2.dist-info/RECORD
neuroglancer-2.41.2.dist-info/WHEEL
neuroglancer-2.41.2.dist-info/top_level.txt
neuroglancer-2.41.2.dist-info/METADATA
neuroglancer-2.41.2.dist-info/licenses/LICENSE
neuroglancer/equivalence_map.py
neuroglancer/coordinate_space.py
neuroglancer/trackable_state.py
neuroglancer/google_credentials.py
neuroglancer/local_volume.py
neuroglancer/downsample_scales.py
neuroglancer/test_utils.py
neuroglancer/segment_colors.py
neuroglancer/async_util.py
neuroglancer/server.py
neuroglancer/downsample.py
neuroglancer/viewer.py
neuroglancer/write_annotations.py
neuroglancer/skeleton.py
neuroglancer/viewer_base.py
neuroglancer/viewer_state.py
neuroglancer/viewer_config_state.py
neuroglancer/read_precomputed_annotations.py
neuroglancer/__init__.py
neuroglancer/test_util.py
neuroglancer/futures.py
neuroglancer/random_token.py
neuroglancer/dvid_credentials.py
neuroglancer/json_wrappers.py
neuroglancer/cli.py
neuroglancer/static_file_server.py
neuroglancer/credentials_provider.py
neuroglancer/url_state.py
neuroglancer/default_credentials_manager.py
neuroglancer/screenshot.py
neuroglancer/json_utils.py
neuroglancer/boss_credentials.py
neuroglancer/chunks.py
neuroglancer/_neuroglancer.abi3.so
neuroglancer/webdriver.py
neuroglancer/static/__init__.py
neuroglancer/static/client/205.5c0e4ae7f56d7f93.js
neuroglancer/static/client/412.2730b6a1889d8051.js
neuroglancer/static/client/412.2730b6a1889d8051.js.map
neuroglancer/static/client/index.html
neuroglancer/static/client/191.2e92ac509dac085a.js.map
neuroglancer/static/client/889.48877a39117a76c2.js.map
neuroglancer/static/client/889.48877a39117a76c2.js
neuroglancer/static/client/main.42f4a67a0b385fe8.css.map
neuroglancer/static/client/451.f4a0ec14850e18f3.js
neuroglancer/static/client/5b383a2480cdc3ac.wasm
neuroglancer/static/client/09f21dcf7b4f13e8.wasm
neuroglancer/static/client/191.2e92ac509dac085a.js
neuroglancer/static/client/e431fe7ba8d0a870.wasm
neuroglancer/static/client/451.f4a0ec14850e18f3.js.map
neuroglancer/static/client/213.03b13076e8c0e996.js.map
neuroglancer/static/client/822.31bbbdbf191a2af5.js.map
