Metadata-Version: 2.4
Name: neuroglancer
Version: 2.41.2
Summary: Python integration for neuroglancer, a WebGL-based viewer for volumetric data
Author-email: Jeremy Maitin-Shepard <jbms@google.com>
License-Expression: Apache-2.0
Project-URL: Repository, https://github.com/google/neuroglancer
Project-URL: Issues, https://github.com/google/neuroglancer/issues
Project-URL: Documentation, https://neuroglancer-docs.web.app
Classifier: Development Status :: 5 - Production/Stable
Classifier: Topic :: Software Development :: Libraries
Requires-Python: >=3.10
License-File: LICENSE
Requires-Dist: atomicwrites>=1.4.1
Requires-Dist: google-apitools>=0.5.32
Requires-Dist: google-auth>=2.38.0
Requires-Dist: numpy>=1.11.0
Requires-Dist: pillow>=3.2.0
Requires-Dist: requests>=2.32.3
Requires-Dist: tornado>=6.4.2
Provides-Extra: webdriver
Requires-Dist: selenium>=4; extra == "webdriver"
Dynamic: license-file
